{
  "columns": [
    {
      "header": "OP 40",
      "values": {
        "Operator Name": "Balaji",
        "Time": "",
        "Machine Name": "HMC!",
        "Parameter 1": "20mm",
        "Parameter 2": "30mm",
        "Parameter 3": "50mm"
      }
    },
    {
      "header": "OP 40",
      "values": {
        "Operator Name": "Balaji",
        "Time": "",
        "Machine Name": "HMC!",
        "Parameter 1": "20mm",
        "Parameter 2": "30mm",
        "Parameter 3": "50mm"
      }
    },
    {
      "header": "OP 40",
      "values": {
        "Operator Name": "Balaji",
        "Time": "",
        "Machine Name": "HMC!",
        "Parameter 1": "20mm",
        "Parameter 2": "30mm",
        "Parameter 3": "50mm"
      }
    },
    {
      "header": "OP 40",
      "values": {
        "Operator Name": "Balaji",
        "Time": "",
        "Machine Name": "HMC!",
        "Parameter 1": "20mm",
        "Parameter 2": "30mm",
        "Parameter 3": "50mm"
      }
    },
    {
      "header": "OP 40",
      "values": {
        "Operator Name": "Balaji",
        "Time": "",
        "Machine Name": "HMC!",
        "Parameter 1": "20mm",
        "Parameter 2": "30mm",
        "Parameter 3": "50mm"
      }
    },
    {
      "header": "OP 40",
      "values": {
        "Operator Name": "Balaji",
        "Time": "",
        "Machine Name": "HMC!",
        "Parameter 1": "20mm",
        "Parameter 2": "30mm",
        "Parameter 3": "50mm"
      }
    },
    {
      "header": "OP 110",
      "values": {
        "Operator Name": "Balaji",
        "Time": "",
        "Machine Name": "HMC!",
        "Parameter 1": "20mm",
        "Parameter 2": "30mm",
        "Parameter 3": "50mm"
      }
    },
    {
      "header": "OP 240",
      "values": {
        "Operator Name": "Balaji",
        "Time": "",
        "Machine Name": "HMC!",
        "Parameter 1": "20mm",
        "Parameter 2": "30mm",
        "Parameter 3": "50mm"
      }
    },
    {
      "header": "OP 210",
      "values": {
        "Operator Name": "Balaji",
        "Time": "",
        "Machine Name": "HMC!",
        "Parameter 1": "20mm",
        "Parameter 2": "30mm",
        "Parameter 3": "50mm"
      }
    }
  ]
}
